opendrift_leeway_webgui/__init__.py
opendrift_leeway_webgui/manage.py
opendrift_leeway_webgui/simulation.py
opendrift_leeway_webgui/api/__init__.py
opendrift_leeway_webgui/api/apps.py
opendrift_leeway_webgui/api/urls.py
opendrift_leeway_webgui/api/v1/__init__.py
opendrift_leeway_webgui/api/v1/serializers.py
opendrift_leeway_webgui/api/v1/urls.py
opendrift_leeway_webgui/api/v1/views.py
opendrift_leeway_webgui/core/__init__.py
opendrift_leeway_webgui/core/logging_formatter.py
opendrift_leeway_webgui/core/settings.py
opendrift_leeway_webgui/core/urls.py
opendrift_leeway_webgui/core/utils.py
opendrift_leeway_webgui/core/wsgi.py
opendrift_leeway_webgui/leeway/__init__.py
opendrift_leeway_webgui/leeway/admin.py
opendrift_leeway_webgui/leeway/apps.py
opendrift_leeway_webgui/leeway/celery.py
opendrift_leeway_webgui/leeway/forms.py
opendrift_leeway_webgui/leeway/models.py
opendrift_leeway_webgui/leeway/tasks.py
opendrift_leeway_webgui/leeway/urls.py
opendrift_leeway_webgui/leeway/utils.py
opendrift_leeway_webgui/leeway/views.py
opendrift_leeway_webgui/leeway/migrations/0001_initial.py
opendrift_leeway_webgui/leeway/migrations/0002_auto_20221205_1342.py
opendrift_leeway_webgui/leeway/migrations/0003_leewaysimulation_user.py
opendrift_leeway_webgui/leeway/migrations/0004_leewaysimulation_simulation_finished.py
opendrift_leeway_webgui/leeway/migrations/0005_leewaysimulation_uuid.py
opendrift_leeway_webgui/leeway/migrations/0006_leewaysimulation_radius.py
opendrift_leeway_webgui/leeway/migrations/0007_leewaysimulation_add_file_fields.py
opendrift_leeway_webgui/leeway/migrations/0008_leewaysimulation_traceback.py
opendrift_leeway_webgui/leeway/migrations/__init__.py
opendrift_leeway_webgui/leeway/static/css/style.css
opendrift_leeway_webgui/leeway/static/image/84eed031-ed5b-4802-a0e9-580b5fd9b93f.png
opendrift_leeway_webgui/leeway/templates/base.html
opendrift_leeway_webgui/leeway/templates/leeway/leewaysimulation_detail.html
opendrift_leeway_webgui-2024.1.0.dist-info/LICENSE
opendrift_leeway_webgui-2024.1.0.dist-info/METADATA
opendrift_leeway_webgui-2024.1.0.dist-info/WHEEL
opendrift_leeway_webgui-2024.1.0.dist-info/top_level.txt
opendrift_leeway_webgui-2024.1.0.dist-info/RECORD
