Metadata-Version: 2.1
Name: opendrift-leeway-webgui
Version: 2024.1.0
Summary: Web GUI for Leeway simulations with OpenDrift
License: Apache2 2.0 License
Project-URL: Homepage, https://leeway.tuerantuer.org
Project-URL: Bug Tracker, https://github.com/digitalfabrik/opendrift-leeway-webgui/issues
Project-URL: Source Code, https://github.com/digitalfabrik/opendrift-leeway-webgui
Keywords: OpenDrift,Leeway,SAR,Search,Rescue,Simulation,Drift
Classifier: Development Status :: 3 - Alpha
Classifier: Framework :: Django
Classifier: Framework :: Django :: 4
Classifier: License :: OSI Approved :: Apache Software License
Classifier: Programming Language :: Python :: 3
Requires-Python: >=3.8
License-File: LICENSE
Requires-Dist: celery
Requires-Dist: django >=4.1
Requires-Dist: djangorestframework
Requires-Dist: django-rest-knox
Requires-Dist: dms2dec
Requires-Dist: drf-spectacular
Requires-Dist: redis
Provides-Extra: dev
Requires-Dist: bumpver ; extra == 'dev'
Requires-Dist: pre-commit ; extra == 'dev'
Requires-Dist: numpy ; extra == 'dev'
Requires-Dist: matplotlib ; extra == 'dev'
Requires-Dist: pylint ; extra == 'dev'
Requires-Dist: pylint-django ; extra == 'dev'
Requires-Dist: pytest ; extra == 'dev'
Requires-Dist: pytest-cov ; extra == 'dev'
Requires-Dist: pytest-django ; extra == 'dev'
Requires-Dist: pytest-env ; extra == 'dev'
